{
  "name": "ds_cntnr_na_addresses_uat",
  "properties": {
    "linkedServiceName": {
      "referenceName": "ls_db_cosmos_customers_na_uat",
      "type": "LinkedServiceReference"
    },
    "folder": {
      "name": "ccore/TDATA-4433/uat"
    },
    "annotations": [],
    "type": "CosmosDbSqlApiCollection",
    "schema": {
      "type": "object",
      "properties": {
        "zipCode": {
          "type": "string"
        },
        "country": {
          "type": "string"
        },
        "city": {
          "type": "string"
        },
        "addressType": {
          "type": "string"
        },
        "fullName": {
          "type": "string"
        },
        "defaultBilling": {
          "type": "boolean"
        },
        "stateName": {
          "type": "string"
        },
        "customerId": {
          "type": "string"
        },
        "linkAddressId": {
          "type": "long"
        },
        "addressLine1": {
          "type": "string"
        },
        "addressLine2": {
          "type": "string"
        },
        "state": {
          "type": "string"
        },
        "countryName": {
          "type": "string"
        },
        "updateTs": {
          "type": "long"
        },
        "email": {
          "type": "string"
        },
        "defaultShipping": {
          "type": "boolean"
        }
      }
    },
    "typeProperties": {
      "collectionName": "address"
    }
  },
  "type": "Microsoft.DataFactory/factories/datasets"
}