{
    "name": "df_profiles_migration_stg",
    "properties": {
        "folder": {
            "name": "ccore-merge/stg"
        },
        "type": "MappingDataFlow",
        "typeProperties": {
            "sources": [
                {
                    "dataset": {
                        "referenceName": "ds_cntnr_na_profile_stg",
                        "type": "DatasetReference"
                    },
                    "name": "NaProfile"
                },
                {
                    "dataset": {
                        "referenceName": "ds_cntnr_ca_profile_stg",
                        "type": "DatasetReference"
                    },
                    "name": "CaProfile"
                }
            ],
            "sinks": [
                {
                    "dataset": {
                        "referenceName": "ds_cntnr_na_profiles_stg",
                        "type": "DatasetReference"
                    },
                    "name": "SinkGlobalProfile"
                },
                {
                    "dataset": {
                        "referenceName": "ds_cntnr_ca_profiles_retained_stg",
                        "type": "DatasetReference"
                    },
                    "name": "SinkCaProfileRetained"
                },
                {
                    "dataset": {
                        "referenceName": "ds_cntnr_na_profiles_retained_stg",
                        "type": "DatasetReference"
                    },
                    "name": "SinkNaProfileRetained"
                }
            ],
            "transformations": [
                {
                    "name": "NaUnionCaRetainedProfiles"
                },
                {
                    "name": "RemoveDuplicateProfilesBasedOnEmails"
                },
                {
                    "name": "SelectPrefLangAndVipinfoFromCa"
                },
                {
                    "name": "NaJoinCaWithLeftOuter"
                },
                {
                    "name": "derivePrefLangAndVipInfo"
                },
                {
                    "name": "removeCaColumns"
                },
                {
                    "name": "SelectCaRetainedProfiles"
                },
                {
                    "name": "EmailVerifiedNa"
                },
                {
                    "name": "RegisteredProfileNa"
                },
                {
                    "name": "LoggedInProfileNa"
                },
                {
                    "name": "ValidEmailDomainProfileNa"
                },
                {
                    "name": "EmailVerifiedCa"
                },
                {
                    "name": "RegisteredProfileCa"
                },
                {
                    "name": "LoggedInProfileCa"
                },
                {
                    "name": "ValidEmailDomainProfileCa"
                }
            ],
            "scriptLines": [
                "source(output(",
                "          bannerOfOrigin as string,",
                "          birthday as string,",
                "          changedBy as string,",
                "          changedFields as string,",
                "          country as string,",
                "          created as long,",
                "          createdBy as string,",
                "          csaInfo as (csaAgentEmail as string, zendeskTicketNumber as string),",
                "          customerFlag as string,",
                "          customerId as string,",
                "          customerSyncStatus as (status as string, updateTs as long, process as string),",
                "          email as string,",
                "          emailHistory as (emailAddress as string, modificationTS as string)[],",
                "          emailVerified as long,",
                "          enrollmentSource as string,",
                "          event as string,",
                "          failedLoginAttempts as long,",
                "          firstName as string,",
                "          flxInfo as (flxEmailOptIn as boolean, loyaltyFlxEmailOptInBanner as string, loyaltyStatus as boolean, points as integer, tier as string, flxNumber as integer, ctNumber as integer, flxTcVersion as string, referralCode as string),",
                "          fraudFlag as string[],",
                "          gender as string,",
                "          homeNumber as long,",
                "          inStoreSignUp as boolean,",
                "          isRegistered as boolean,",
                "          janrainUuid as string,",
                "          lastFailedLogin as string,",
                "          lastLogin as string,",
                "          lastName as string,",
                "          militaryExpiryDate as string,",
                "          militaryRequestId as string,",
                "          militaryStatus as string,",
                "          mobileNumber as long,",
                "          oldCsCid as string,",
                "          oldEbCid as string,",
                "          oldFaCid as string,",
                "          oldFlCid as string,",
                "          oldFlcaCid as string,",
                "          oldFsCid as string,",
                "          oldKflCid as string,",
                "          oldLflCid as string,",
                "          optIns as (banner as string)[],",
                "          password as string,",
                "          passwordChangeDate as string,",
                "          preferredLanguage as string,",
                "          preferredStores as (CS as (city as string, country as string, division as string, isocodeShort as string, latitude as string, line1 as string, line2 as string, longitude as string, name as string, phone as string, state as string, status as string, storeId as string, zipcode as string), FA as (city as string, country as string, division as string, isocodeShort as string, latitude as string, line1 as string, line2 as string, longitude as string, name as string, phone as string, state as string, status as string, storeId as string, zipcode as string), FL as (city as string, country as string, division as string, isocodeShort as string, latitude as string, line1 as string, line2 as string, longitude as string, name as string, phone as string, state as string, status as string, storeId as string, zipcode as string), KFL as (city as string, country as string, division as string, isocodeShort as string, latitude as string, line1 as string, line2 as string, longitude as string, name as string, phone as string, state as string, status as string, storeId as string, zipcode as string)),",
                "          previousEmail as string,",
                "          profileStatus as string,",
                "          region as string,",
                "          relateCustomerId as string,",
                "          relateFailure as boolean,",
                "          retailStoreId as integer,",
                "          schDefaultBillingAddressLine1 as string,",
                "          schDefaultShippingAddressLine1 as string,",
                "          storeNumber as string,",
                "          streetAddress as string,",
                "          token as string,",
                "          updateTs as long,",
                "          updateTsExceptLogin as long,",
                "          vipInfo as (dollarsNeedToSpend as (currencyIso as string, formattedValue as string, value as integer), loyaltyMinThreshold as (currencyIso as string, formattedValue as string, value as integer), dollarsSpent as (currencyIso as string, formattedValue as string, value as integer), loyaltyTargetThreshold as (currencyIso as string, formattedValue as string, value as integer), vipNumber as string, lastLevelUpdateDateHyb as long, lastLevelMoveDate as long, loyaltyExpireDate as long, isVip as boolean, lifeTimePoints as long, status as string),",
                "          webhookMessageStatus as string,",
                "          xstoreId as string,",
                "          zipCode as string",
                "     ),",
                "     allowSchemaDrift: true,",
                "     validateSchema: false,",
                "     format: 'document') ~> NaProfile",
                "source(output(",
                "          bannerOfOrigin as string,",
                "          birthday as string,",
                "          changedBy as string,",
                "          changedFields as string,",
                "          country as string,",
                "          created as long,",
                "          createdBy as string,",
                "          csaInfo as (csaAgentEmail as string, zendeskTicketNumber as string),",
                "          customerFlag as string,",
                "          customerId as string,",
                "          customerSyncStatus as (status as string, updateTs as long, process as string),",
                "          email as string,",
                "          emailHistory as (emailAddress as string, modificationTS as string)[],",
                "          emailVerified as long,",
                "          enrollmentSource as string,",
                "          event as string,",
                "          failedLoginAttempts as long,",
                "          firstName as string,",
                "          flxInfo as (flxEmailOptIn as boolean, loyaltyFlxEmailOptInBanner as string, loyaltyStatus as boolean, points as integer, tier as string, flxNumber as integer, ctNumber as integer, flxTcVersion as string, referralCode as string),",
                "          fraudFlag as string[],",
                "          gender as string,",
                "          homeNumber as long,",
                "          inStoreSignUp as boolean,",
                "          isRegistered as boolean,",
                "          janrainUuid as string,",
                "          lastFailedLogin as string,",
                "          lastLogin as string,",
                "          lastName as string,",
                "          militaryExpiryDate as string,",
                "          militaryRequestId as string,",
                "          militaryStatus as string,",
                "          mobileNumber as long,",
                "          oldCsCid as string,",
                "          oldEbCid as string,",
                "          oldFaCid as string,",
                "          oldFlCid as string,",
                "          oldFlcaCid as string,",
                "          oldFsCid as string,",
                "          oldKflCid as string,",
                "          oldLflCid as string,",
                "          optIns as (banner as string)[],",
                "          password as string,",
                "          passwordChangeDate as string,",
                "          preferredLanguage as string,",
                "          preferredStores as (CS as (city as string, country as string, division as string, isocodeShort as string, latitude as string, line1 as string, line2 as string, longitude as string, name as string, phone as string, state as string, status as string, storeId as string, zipcode as string), FA as (city as string, country as string, division as string, isocodeShort as string, latitude as string, line1 as string, line2 as string, longitude as string, name as string, phone as string, state as string, status as string, storeId as string, zipcode as string), FL as (city as string, country as string, division as string, isocodeShort as string, latitude as string, line1 as string, line2 as string, longitude as string, name as string, phone as string, state as string, status as string, storeId as string, zipcode as string), KFL as (city as string, country as string, division as string, isocodeShort as string, latitude as string, line1 as string, line2 as string, longitude as string, name as string, phone as string, state as string, status as string, storeId as string, zipcode as string)),",
                "          previousEmail as string,",
                "          profileStatus as string,",
                "          region as string,",
                "          relateCustomerId as string,",
                "          relateFailure as boolean,",
                "          retailStoreId as string,",
                "          schDefaultBillingAddressLine1 as string,",
                "          schDefaultShippingAddressLine1 as string,",
                "          storeNumber as string,",
                "          streetAddress as string,",
                "          token as string,",
                "          updateTs as long,",
                "          updateTsExceptLogin as long,",
                "          vipInfo as (dollarsNeedToSpend as (currencyIso as string, formattedValue as string, value as integer), loyaltyMinThreshold as (currencyIso as string, formattedValue as string, value as integer), dollarsSpent as (currencyIso as string, formattedValue as string, value as integer), loyaltyTargetThreshold as (currencyIso as string, formattedValue as string, value as integer), vipNumber as string, lastLevelUpdateDateHyb as long, lastLevelMoveDate as long, loyaltyExpireDate as long, isVip as boolean, lifeTimePoints as long, status as string),",
                "          webhookMessageStatus as string,",
                "          xstoreId as string,",
                "          zipCode as string",
                "     ),",
                "     allowSchemaDrift: true,",
                "     validateSchema: false,",
                "     format: 'document') ~> CaProfile",
                "ValidEmailDomainProfileNa, SelectCaRetainedProfiles union(byName: true)~> NaUnionCaRetainedProfiles",
                "NaUnionCaRetainedProfiles aggregate(groupBy(email),",
                "     each(match(name!='email'), $$ = first($$))) ~> RemoveDuplicateProfilesBasedOnEmails",
                "SelectCaRetainedProfiles select(mapColumn(",
                "          email,",
                "          preferredLanguage,",
                "          vipInfo",
                "     ),",
                "     skipDuplicateMapInputs: true,",
                "     skipDuplicateMapOutputs: true) ~> SelectPrefLangAndVipinfoFromCa",
                "RemoveDuplicateProfilesBasedOnEmails, SelectPrefLangAndVipinfoFromCa join(RemoveDuplicateProfilesBasedOnEmails@email == SelectPrefLangAndVipinfoFromCa@email,",
                "     joinType:'left',",
                "     matchType:'exact',",
                "     ignoreSpaces: false,",
                "     broadcast: 'auto')~> NaJoinCaWithLeftOuter",
                "NaJoinCaWithLeftOuter derive(preferredLanguage = iif(equalsIgnoreCase(SelectPrefLangAndVipinfoFromCa@preferredLanguage, 'fr'), 'fr', 'en'),",
                "          vipInfo = iif(isNull(SelectPrefLangAndVipinfoFromCa@vipInfo), RemoveDuplicateProfilesBasedOnEmails@vipInfo, SelectPrefLangAndVipinfoFromCa@vipInfo)) ~> derivePrefLangAndVipInfo",
                "derivePrefLangAndVipInfo select(mapColumn(",
                "          email = RemoveDuplicateProfilesBasedOnEmails@email,",
                "          bannerOfOrigin,",
                "          birthday,",
                "          changedBy,",
                "          changedFields,",
                "          country,",
                "          created,",
                "          createdBy,",
                "          csaInfo,",
                "          customerFlag,",
                "          customerId,",
                "          customerSyncStatus,",
                "          emailHistory,",
                "          emailVerified,",
                "          enrollmentSource,",
                "          event,",
                "          failedLoginAttempts,",
                "          firstName,",
                "          flxInfo,",
                "          fraudFlag,",
                "          gender,",
                "          homeNumber,",
                "          inStoreSignUp,",
                "          isRegistered,",
                "          janrainUuid,",
                "          lastFailedLogin,",
                "          lastLogin,",
                "          lastName,",
                "          militaryExpiryDate,",
                "          militaryRequestId,",
                "          militaryStatus,",
                "          mobileNumber,",
                "          oldCsCid,",
                "          oldEbCid,",
                "          oldFaCid,",
                "          oldFlCid,",
                "          oldFlcaCid,",
                "          oldFsCid,",
                "          oldKflCid,",
                "          oldLflCid,",
                "          optIns,",
                "          password,",
                "          passwordChangeDate,",
                "          preferredLanguage,",
                "          preferredStores,",
                "          previousEmail,",
                "          profileStatus,",
                "          region,",
                "          relateCustomerId,",
                "          relateFailure,",
                "          retailStoreId,",
                "          schDefaultBillingAddressLine1,",
                "          schDefaultShippingAddressLine1,",
                "          storeNumber,",
                "          streetAddress,",
                "          token,",
                "          updateTs,",
                "          updateTsExceptLogin,",
                "          vipInfo,",
                "          webhookMessageStatus,",
                "          xstoreId,",
                "          zipCode",
                "     ),",
                "     skipDuplicateMapInputs: true,",
                "     skipDuplicateMapOutputs: true) ~> removeCaColumns",
                "ValidEmailDomainProfileCa select(mapColumn(",
                "          bannerOfOrigin,",
                "          birthday,",
                "          changedBy,",
                "          changedFields,",
                "          country,",
                "          created,",
                "          createdBy,",
                "          csaInfo,",
                "          customerFlag,",
                "          customerId,",
                "          email,",
                "          emailHistory,",
                "          emailVerified,",
                "          event,",
                "          failedLoginAttempts,",
                "          firstName,",
                "          flxInfo,",
                "          fraudFlag,",
                "          homeNumber,",
                "          inStoreSignUp,",
                "          isRegistered,",
                "          janrainUuid,",
                "          lastFailedLogin,",
                "          lastLogin,",
                "          lastName,",
                "          militaryExpiryDate,",
                "          militaryRequestId,",
                "          militaryStatus,",
                "          mobileNumber,",
                "          oldCsCid,",
                "          oldEbCid,",
                "          oldFaCid,",
                "          oldFlCid,",
                "          oldFlcaCid,",
                "          oldFsCid,",
                "          oldKflCid,",
                "          oldLflCid,",
                "          optIns,",
                "          passwordChangeDate,",
                "          preferredLanguage,",
                "          previousEmail,",
                "          profileStatus,",
                "          relateFailure,",
                "          schDefaultBillingAddressLine1,",
                "          schDefaultShippingAddressLine1,",
                "          storeNumber,",
                "          token,",
                "          updateTs,",
                "          updateTsExceptLogin,",
                "          vipInfo,",
                "          webhookMessageStatus,",
                "          xstoreId,",
                "          zipCode",
                "     ),",
                "     skipDuplicateMapInputs: true,",
                "     skipDuplicateMapOutputs: true) ~> SelectCaRetainedProfiles",
                "NaProfile filter(not(and(isNull(emailVerified), not(greaterOrEqual(toTimestamp(toLong(toString(created)),'yyyy-MM-dd HH:mm:ss'), subDays(currentTimestamp(), 365)))))) ~> EmailVerifiedNa",
                "EmailVerifiedNa filter(not(and(isRegistered == toBoolean('FALSE'), not(greaterOrEqual(toTimestamp(toLong(toString(created)),'yyyy-MM-dd HH:mm:ss'), subDays(currentTimestamp(), 365)))))) ~> RegisteredProfileNa",
                "RegisteredProfileNa filter(not(iif(and(isNull(lastLogin),or(bannerOfOrigin == 'flca',bannerOfOrigin == 'csca')), toBoolean('true'), iif(isNull(bannerOfOrigin), toBoolean('true'), and(not(greaterOrEqual(lastLogin,toString(subDays(currentTimestamp(),365)))), or(bannerOfOrigin == 'flca',bannerOfOrigin == 'csca')))))) ~> LoggedInProfileNa",
                "LoggedInProfileNa filter(rlike(email,'^((?!soledupsneakz.club|atolemdro.com|aceslaya.club|shaszn.xyz|muhlach.com|luigisneaks.com|davidssnkrs.club|qq.com*|coneysoles.us|lizama.xyz|sincarts.com|hypecopped.com|youcopped.pw|dadswag.club|randys.cash|yididu.com|jimmyshoetron.com|15p.pw|ericwenhy.club|cookgod.club|og-cooks.com|guccicooks.com|shophiddenheat.com|amplifykicks.club|solesecret.xyz|tfn27.xyz|smy666.com|isellsneakers.com|jscarts.com|tiktokfreefollowers.com|solarcooks.xyz|jimmartoccia.club|wowitslem.com|kaltashi.club|thecelibate.club|ncshoes.club|coppedbyepic.us|nate123.club|solestrikes.com|snkrmail.com|jjsamson.club|coatalcf.club|sacredslots.com|33mail.com|caspermika.club|tn1220.club|dontfuckwithme.club|next-mail.info|cart198.club|sneakermonekys.club|mattykickz.club|ryucooks.club|hypexchange.net|cristianjgarcia.club|figsoles.club|laflame.club|troxer.club|bruhszn.club|naeucop.club|kxvcop.club|resellersunite.com|worldwidesneakers.club|doncarted.club|aiobotz.com|0815.ru|0wnd.net|0wnd.org|10minutemail.co.za|10minutemail.com|123-m.com|1fsdfdsfsdf.tk|1pad.de|20minutemail.com|21cn.com|2fdgdfgdfgdf.tk|2prong.com|30minutemail.com|33mail.com|3trtretgfrfe.tk|4gfdsgfdgfd.tk|4warding.com|5ghgfhfghfgh.tk|6hjgjhgkilkj.tk|6paq.com|7tags.com|9ox.net|a-bc.net|agedmail.com|ama-trade.de|amilegit.com|amiri.net|amiriindustries.com|anonmails.de|anonymbox.com|antichef.com|antichef.net|antireg.ru|antispam.de|antispammail.de|armyspy.com|artman-conception.com|azmeil.tk|baxomale.ht.cx|beefmilk.com|bigstring.com|binkmail.com|bio-muesli.net|bobmail.info|bodhi.lawlita.com|bofthew.com|bootybay.de|boun.cr|bouncr.com|breakthru.com|brefmail.com|bsnow.net|bspamfree.org|bugmenot.com|bund.us|burstmail.info|buymoreplays.com|byom.de|c2.hu|card.zp.ua|casualdx.com|cek.pm|centermail.com|centermail.net|chammy.info|childsavetrust.org|chogmail.com|choicemail1.com|clixser.com|cmail.net|cmail.org|coldemail.info|cool.fr.nf|courriel.fr.nf|courrieltemporaire.com|crapmail.org|cust.in|cuvox.de|d3p.dk|dacoolest.com|dandikmail.com|dayrep.com|dcemail.com|deadaddress.com|deadspam.com|delikkt.de|despam.it|despammed.com|devnullmail.com|dfgh.net|digitalsanctuary.com|dingbone.com|disposableaddress.com|disposableemailaddresses.com|disposableinbox.com|dispose.it|dispostable.com|dodgeit.com|dodgit.com|donemail.ru|dontreg.com|dontsendmespam.de|drdrb.net|dump-email.info|dumpandjunk.com|dumpyemail.com|e-mail.com|e-mail.org|e4ward.com|easytrashmail.com|einmalmail.de|einrot.com|eintagsmail.de|emailgo.de|emailias.com|emaillime.com|emailsensei.com|emailtemporanea.com|emailtemporanea.net|emailtemporar.ro|emailtemporario.com.br|emailthe.net|emailtmp.com|emailwarden.com|emailx.at.hm|emailxfer.com|emeil.in|emeil.ir|emz.net|ero-tube.org|evopo.com|explodemail.com|express.net.ua|eyepaste.com|fakeinbox.com|fakeinformation.com|fansworldwide.de|fantasymail.de|fightallspam.com|filzmail.com|fivemail.de|fleckens.hu|frapmail.com|friendlymail.co.uk|fuckingduh.com|fudgerub.com|fyii.de|garliclife.com|gehensiemirnichtaufdensack.de|get2mail.fr|getairmail.com|getmails.eu|getonemail.com|giantmail.de|girlsundertheinfluence.com|gishpuppy.com|gmial.com|goemailgo.com|gotmail.net|gotmail.org|gotti.otherinbox.com|great-host.in|greensloth.com|grr.la|gsrv.co.uk|guerillamail.biz|guerillamail.com|guerrillamail.biz|guerrillamail.com|guerrillamail.de|guerrillamail.info|guerrillamail.net|guerrillamail.org|guerrillamailblock.com|gustr.com|harakirimail.com|hat-geld.de|hatespam.org|herp.in|hidemail.de|hidzz.com|hmamail.com|hopemail.biz|ieh-mail.de|ikbenspamvrij.nl|imails.info|inbax.tk|inbox.si|inboxalias.com|inboxclean.com|inboxclean.org|infocom.zp.ua|instant-mail.de|ip6.li|irish2me.com|iwi.net|jetable.com|jetable.fr.nf|jetable.net|jetable.org|jnxjn.com|jourrapide.com|jsrsolutions.com|kasmail.com|kaspop.com|killmail.com|killmail.net|klassmaster.com|klzlk.com|koszmail.pl|kurzepost.de|lawlita.com|letthemeatspam.com|lhsdv.com|lifebyfood.com|link2mail.net|litedrop.com|lol.ovpn.to|lolfreak.net|lookugly.com|lortemail.dk|lr78.com|lroid.com|lukop.dk|m21.cc|mail-filter.com|mail-temporaire.fr|mail.by|mail.mezimages.net|mail.zp.ua|mail1a.de|mail21.cc|mail2rss.org|mail333.com|mailbidon.com|mailbiz.biz|mailblocks.com|mailbucket.org|mailcat.biz|mailcatch.com|mailde.de|mailde.info|maildrop.cc|maileimer.de|mailexpire.com|mailfa.tk|mailforspam.com|mailfreeonline.com|mailguard.me|mailin8r.com|mailinater.com|mailinator.com|mailinator.net|mailinator.org|mailinator2.com|mailincubator.com|mailismagic.com|mailme.lv|mailme24.com|mailmetrash.com|mailmoat.com|mailms.com|mailnesia.com|mailnull.com|mailorg.org|mailpick.biz|mailrock.biz|mailscrap.com|mailshell.com|mailsiphon.com|mailtemp.info|mailtome.de|mailtothis.com|mailtrash.net|mailtv.net|mailtv.tv|mailzilla.com|makemetheking.com|manybrain.com|mbx.cc|mega.zik.dj|meinspamschutz.de|meltmail.com|messagebeamer.de|mezimages.net|ministry-of-silly-walks.de|mintemail.com|misterpinball.de|moncourrier.fr.nf|monemail.fr.nf|monmail.fr.nf|monumentmail.com|mt2009.com|mt2014.com|mycard.net.ua|mycleaninbox.net|mymail-in.net|mypacks.net|mypartyclip.de|myphantomemail.com|mysamp.de|mytempemail.com|mytempmail.com|mytrashmail.com|nabuma.com|neomailbox.com|nepwk.com|nervmich.net|nervtmich.net|netmails.com|netmails.net|neverbox.com|nice-4u.com|nincsmail.hu|nnh.com|no-spam.ws|noblepioneer.com|nomail.pw|nomail.xl.cx|nomail2me.com|nomorespamemails.com|nospam.ze.tc|nospam4.us|nospamfor.us|nospammail.net|notmailinator.com|nowhere.org|nowmymail.com|nurfuerspam.de|nus.edu.sg|objectmail.com|obobbo.com|odnorazovoe.ru|oneoffemail.com|onewaymail.com|onlatedotcom.info|online.ms|opayq.com|ordinaryamerican.net|otherinbox.com|ovpn.to|owlpic.com|pancakemail.com|pcusers.otherinbox.com|pjjkp.com|plexolan.de|poczta.onet.pl|politikerclub.de|poofy.org|pookmail.com|privacy.net|privatdemail.net|proxymail.eu|prtnx.com|putthisinyourspamdatabase.com|putthisinyourspamdatabase.com|qq.com|quickinbox.com|rcpt.at|reallymymail.com|realtyalerts.ca|recode.me|recursor.net|reliable-mail.com|rhyta.com|rmqkr.net|royal.net|rtrtr.com|s0ny.net|safe-mail.net|safersignup.de|safetymail.info|safetypost.de|saynotospams.com|schafmail.de|schrott-email.de|secretemail.de|secure-mail.biz|senseless-entertainment.com|services391.com|sharklasers.com|shieldemail.com|shiftmail.com|shitmail.me|shitware.nl|shmeriously.com|shortmail.net|sibmail.com|sinnlos-mail.de|slapsfromlastnight.com|slaskpost.se|smashmail.de|smellfear.com|snakemail.com|sneakemail.com|sneakmail.de|snkmail.com|sofimail.com|solvemail.info|sogetthis.com|soodonims.com|spam4.me|spamail.de|spamarrest.com|spambob.net|spambog.ru|spambox.us|spamcannon.com|spamcannon.net|spamcon.org|spamcorptastic.com|spamcowboy.com|spamcowboy.net|spamcowboy.org|spamday.com|spamex.com|spamfree.eu|spamfree24.com|spamfree24.de|spamfree24.org|spamgoes.in|spamgourmet.com|spamgourmet.net|spamgourmet.org|spamherelots.com|spamherelots.com|spamhereplease.com|spamhereplease.com|spamhole.com|spamify.com|spaml.de|spammotel.com|spamobox.com|spamslicer.com|spamspot.com|spamthis.co.uk|spamtroll.net|speed.1s.fr|spoofmail.de|stuffmail.de|super-auswahl.de|supergreatmail.com|supermailer.jp|superrito.com|superstachel.de|suremail.info|talkinator.com|teewars.org|teleworm.com|teleworm.us|temp-mail.org|temp-mail.ru|tempe-mail.com|tempemail.co.za|tempemail.com|tempemail.net|tempemail.net|tempinbox.co.uk|tempinbox.com|tempmail.eu|tempmaildemo.com|tempmailer.com|tempmailer.de|tempomail.fr|temporaryemail.net|temporaryforwarding.com|temporaryinbox.com|temporarymailaddress.com|tempthe.net|thankyou2010.com|thc.st|thelimestones.com|thisisnotmyrealemail.com|thismail.net|throwawayemailaddress.com|tilien.com|tittbit.in|tizi.com|tmailinator.com|toomail.biz|topranklist.de|tradermail.info|trash-mail.at|trash-mail.com|trash-mail.de|trash2009.com|trashdevil.com|trashemail.de|trashmail.at|trashmail.com|trashmail.de|trashmail.me|trashmail.net|trashmail.org|trashymail.com|trialmail.de|trillianpro.com|twinmail.de|tyldd.com|uggsrock.com|umail.net|uroid.com|us.af|venompen.com|veryrealemail.com|viditag.com|viralplays.com|vpn.st|vsimcard.com|vubby.com|wasteland.rfc822.org|webemail.me|weg-werf-email.de|wegwerf-emails.de|wegwerfadresse.de|wegwerfemail.com|wegwerfemail.de|wegwerfmail.de|wegwerfmail.info|wegwerfmail.net|wegwerfmail.org|wh4f.org|whyspam.me|willhackforfood.biz|willselfdestruct.com|winemaven.info|wronghead.com|www.e4ward.com|www.mailinator.com|wwwnew.eu|x.ip6.li|xagloo.com|xemaps.com|xents.com|xmaily.com|xoxy.net|yep.it|yogamaven.com|yopmail.com|yopmail.fr|yopmail.net|yourdomain.com|yuurok.com|z1p.biz|za.com|zehnminuten.de|zehnminutenmail.de|zippymail.info|zoemail.net|zomg.info).)*$')) ~> ValidEmailDomainProfileNa",
                "CaProfile filter(not(and(isNull(emailVerified), not(greaterOrEqual(toTimestamp(toLong(toString(created)),'yyyy-MM-dd HH:mm:ss'), subDays(currentTimestamp(), 365)))))) ~> EmailVerifiedCa",
                "EmailVerifiedCa filter(not(and(isRegistered == toBoolean('FALSE'), not(greaterOrEqual(toTimestamp(toLong(toString(created)),'yyyy-MM-dd HH:mm:ss'), subDays(currentTimestamp(), 365)))))) ~> RegisteredProfileCa",
                "RegisteredProfileCa filter(not(iif(and(isNull(lastLogin),or(bannerOfOrigin == 'flca',bannerOfOrigin == 'csca')), toBoolean('true'), iif(isNull(bannerOfOrigin), toBoolean('true'), and(not(greaterOrEqual(lastLogin,toString(subDays(currentTimestamp(),365)))), or(bannerOfOrigin == 'flca',bannerOfOrigin == 'csca')))))) ~> LoggedInProfileCa",
                "LoggedInProfileCa filter(rlike(email,'^((?!soledupsneakz.club|atolemdro.com|aceslaya.club|shaszn.xyz|muhlach.com|luigisneaks.com|davidssnkrs.club|qq.com*|coneysoles.us|lizama.xyz|sincarts.com|hypecopped.com|youcopped.pw|dadswag.club|randys.cash|yididu.com|jimmyshoetron.com|15p.pw|ericwenhy.club|cookgod.club|og-cooks.com|guccicooks.com|shophiddenheat.com|amplifykicks.club|solesecret.xyz|tfn27.xyz|smy666.com|isellsneakers.com|jscarts.com|tiktokfreefollowers.com|solarcooks.xyz|jimmartoccia.club|wowitslem.com|kaltashi.club|thecelibate.club|ncshoes.club|coppedbyepic.us|nate123.club|solestrikes.com|snkrmail.com|jjsamson.club|coatalcf.club|sacredslots.com|33mail.com|caspermika.club|tn1220.club|dontfuckwithme.club|next-mail.info|cart198.club|sneakermonekys.club|mattykickz.club|ryucooks.club|hypexchange.net|cristianjgarcia.club|figsoles.club|laflame.club|troxer.club|bruhszn.club|naeucop.club|kxvcop.club|resellersunite.com|worldwidesneakers.club|doncarted.club|aiobotz.com|0815.ru|0wnd.net|0wnd.org|10minutemail.co.za|10minutemail.com|123-m.com|1fsdfdsfsdf.tk|1pad.de|20minutemail.com|21cn.com|2fdgdfgdfgdf.tk|2prong.com|30minutemail.com|33mail.com|3trtretgfrfe.tk|4gfdsgfdgfd.tk|4warding.com|5ghgfhfghfgh.tk|6hjgjhgkilkj.tk|6paq.com|7tags.com|9ox.net|a-bc.net|agedmail.com|ama-trade.de|amilegit.com|amiri.net|amiriindustries.com|anonmails.de|anonymbox.com|antichef.com|antichef.net|antireg.ru|antispam.de|antispammail.de|armyspy.com|artman-conception.com|azmeil.tk|baxomale.ht.cx|beefmilk.com|bigstring.com|binkmail.com|bio-muesli.net|bobmail.info|bodhi.lawlita.com|bofthew.com|bootybay.de|boun.cr|bouncr.com|breakthru.com|brefmail.com|bsnow.net|bspamfree.org|bugmenot.com|bund.us|burstmail.info|buymoreplays.com|byom.de|c2.hu|card.zp.ua|casualdx.com|cek.pm|centermail.com|centermail.net|chammy.info|childsavetrust.org|chogmail.com|choicemail1.com|clixser.com|cmail.net|cmail.org|coldemail.info|cool.fr.nf|courriel.fr.nf|courrieltemporaire.com|crapmail.org|cust.in|cuvox.de|d3p.dk|dacoolest.com|dandikmail.com|dayrep.com|dcemail.com|deadaddress.com|deadspam.com|delikkt.de|despam.it|despammed.com|devnullmail.com|dfgh.net|digitalsanctuary.com|dingbone.com|disposableaddress.com|disposableemailaddresses.com|disposableinbox.com|dispose.it|dispostable.com|dodgeit.com|dodgit.com|donemail.ru|dontreg.com|dontsendmespam.de|drdrb.net|dump-email.info|dumpandjunk.com|dumpyemail.com|e-mail.com|e-mail.org|e4ward.com|easytrashmail.com|einmalmail.de|einrot.com|eintagsmail.de|emailgo.de|emailias.com|emaillime.com|emailsensei.com|emailtemporanea.com|emailtemporanea.net|emailtemporar.ro|emailtemporario.com.br|emailthe.net|emailtmp.com|emailwarden.com|emailx.at.hm|emailxfer.com|emeil.in|emeil.ir|emz.net|ero-tube.org|evopo.com|explodemail.com|express.net.ua|eyepaste.com|fakeinbox.com|fakeinformation.com|fansworldwide.de|fantasymail.de|fightallspam.com|filzmail.com|fivemail.de|fleckens.hu|frapmail.com|friendlymail.co.uk|fuckingduh.com|fudgerub.com|fyii.de|garliclife.com|gehensiemirnichtaufdensack.de|get2mail.fr|getairmail.com|getmails.eu|getonemail.com|giantmail.de|girlsundertheinfluence.com|gishpuppy.com|gmial.com|goemailgo.com|gotmail.net|gotmail.org|gotti.otherinbox.com|great-host.in|greensloth.com|grr.la|gsrv.co.uk|guerillamail.biz|guerillamail.com|guerrillamail.biz|guerrillamail.com|guerrillamail.de|guerrillamail.info|guerrillamail.net|guerrillamail.org|guerrillamailblock.com|gustr.com|harakirimail.com|hat-geld.de|hatespam.org|herp.in|hidemail.de|hidzz.com|hmamail.com|hopemail.biz|ieh-mail.de|ikbenspamvrij.nl|imails.info|inbax.tk|inbox.si|inboxalias.com|inboxclean.com|inboxclean.org|infocom.zp.ua|instant-mail.de|ip6.li|irish2me.com|iwi.net|jetable.com|jetable.fr.nf|jetable.net|jetable.org|jnxjn.com|jourrapide.com|jsrsolutions.com|kasmail.com|kaspop.com|killmail.com|killmail.net|klassmaster.com|klzlk.com|koszmail.pl|kurzepost.de|lawlita.com|letthemeatspam.com|lhsdv.com|lifebyfood.com|link2mail.net|litedrop.com|lol.ovpn.to|lolfreak.net|lookugly.com|lortemail.dk|lr78.com|lroid.com|lukop.dk|m21.cc|mail-filter.com|mail-temporaire.fr|mail.by|mail.mezimages.net|mail.zp.ua|mail1a.de|mail21.cc|mail2rss.org|mail333.com|mailbidon.com|mailbiz.biz|mailblocks.com|mailbucket.org|mailcat.biz|mailcatch.com|mailde.de|mailde.info|maildrop.cc|maileimer.de|mailexpire.com|mailfa.tk|mailforspam.com|mailfreeonline.com|mailguard.me|mailin8r.com|mailinater.com|mailinator.com|mailinator.net|mailinator.org|mailinator2.com|mailincubator.com|mailismagic.com|mailme.lv|mailme24.com|mailmetrash.com|mailmoat.com|mailms.com|mailnesia.com|mailnull.com|mailorg.org|mailpick.biz|mailrock.biz|mailscrap.com|mailshell.com|mailsiphon.com|mailtemp.info|mailtome.de|mailtothis.com|mailtrash.net|mailtv.net|mailtv.tv|mailzilla.com|makemetheking.com|manybrain.com|mbx.cc|mega.zik.dj|meinspamschutz.de|meltmail.com|messagebeamer.de|mezimages.net|ministry-of-silly-walks.de|mintemail.com|misterpinball.de|moncourrier.fr.nf|monemail.fr.nf|monmail.fr.nf|monumentmail.com|mt2009.com|mt2014.com|mycard.net.ua|mycleaninbox.net|mymail-in.net|mypacks.net|mypartyclip.de|myphantomemail.com|mysamp.de|mytempemail.com|mytempmail.com|mytrashmail.com|nabuma.com|neomailbox.com|nepwk.com|nervmich.net|nervtmich.net|netmails.com|netmails.net|neverbox.com|nice-4u.com|nincsmail.hu|nnh.com|no-spam.ws|noblepioneer.com|nomail.pw|nomail.xl.cx|nomail2me.com|nomorespamemails.com|nospam.ze.tc|nospam4.us|nospamfor.us|nospammail.net|notmailinator.com|nowhere.org|nowmymail.com|nurfuerspam.de|nus.edu.sg|objectmail.com|obobbo.com|odnorazovoe.ru|oneoffemail.com|onewaymail.com|onlatedotcom.info|online.ms|opayq.com|ordinaryamerican.net|otherinbox.com|ovpn.to|owlpic.com|pancakemail.com|pcusers.otherinbox.com|pjjkp.com|plexolan.de|poczta.onet.pl|politikerclub.de|poofy.org|pookmail.com|privacy.net|privatdemail.net|proxymail.eu|prtnx.com|putthisinyourspamdatabase.com|putthisinyourspamdatabase.com|qq.com|quickinbox.com|rcpt.at|reallymymail.com|realtyalerts.ca|recode.me|recursor.net|reliable-mail.com|rhyta.com|rmqkr.net|royal.net|rtrtr.com|s0ny.net|safe-mail.net|safersignup.de|safetymail.info|safetypost.de|saynotospams.com|schafmail.de|schrott-email.de|secretemail.de|secure-mail.biz|senseless-entertainment.com|services391.com|sharklasers.com|shieldemail.com|shiftmail.com|shitmail.me|shitware.nl|shmeriously.com|shortmail.net|sibmail.com|sinnlos-mail.de|slapsfromlastnight.com|slaskpost.se|smashmail.de|smellfear.com|snakemail.com|sneakemail.com|sneakmail.de|snkmail.com|sofimail.com|solvemail.info|sogetthis.com|soodonims.com|spam4.me|spamail.de|spamarrest.com|spambob.net|spambog.ru|spambox.us|spamcannon.com|spamcannon.net|spamcon.org|spamcorptastic.com|spamcowboy.com|spamcowboy.net|spamcowboy.org|spamday.com|spamex.com|spamfree.eu|spamfree24.com|spamfree24.de|spamfree24.org|spamgoes.in|spamgourmet.com|spamgourmet.net|spamgourmet.org|spamherelots.com|spamherelots.com|spamhereplease.com|spamhereplease.com|spamhole.com|spamify.com|spaml.de|spammotel.com|spamobox.com|spamslicer.com|spamspot.com|spamthis.co.uk|spamtroll.net|speed.1s.fr|spoofmail.de|stuffmail.de|super-auswahl.de|supergreatmail.com|supermailer.jp|superrito.com|superstachel.de|suremail.info|talkinator.com|teewars.org|teleworm.com|teleworm.us|temp-mail.org|temp-mail.ru|tempe-mail.com|tempemail.co.za|tempemail.com|tempemail.net|tempemail.net|tempinbox.co.uk|tempinbox.com|tempmail.eu|tempmaildemo.com|tempmailer.com|tempmailer.de|tempomail.fr|temporaryemail.net|temporaryforwarding.com|temporaryinbox.com|temporarymailaddress.com|tempthe.net|thankyou2010.com|thc.st|thelimestones.com|thisisnotmyrealemail.com|thismail.net|throwawayemailaddress.com|tilien.com|tittbit.in|tizi.com|tmailinator.com|toomail.biz|topranklist.de|tradermail.info|trash-mail.at|trash-mail.com|trash-mail.de|trash2009.com|trashdevil.com|trashemail.de|trashmail.at|trashmail.com|trashmail.de|trashmail.me|trashmail.net|trashmail.org|trashymail.com|trialmail.de|trillianpro.com|twinmail.de|tyldd.com|uggsrock.com|umail.net|uroid.com|us.af|venompen.com|veryrealemail.com|viditag.com|viralplays.com|vpn.st|vsimcard.com|vubby.com|wasteland.rfc822.org|webemail.me|weg-werf-email.de|wegwerf-emails.de|wegwerfadresse.de|wegwerfemail.com|wegwerfemail.de|wegwerfmail.de|wegwerfmail.info|wegwerfmail.net|wegwerfmail.org|wh4f.org|whyspam.me|willhackforfood.biz|willselfdestruct.com|winemaven.info|wronghead.com|www.e4ward.com|www.mailinator.com|wwwnew.eu|x.ip6.li|xagloo.com|xemaps.com|xents.com|xmaily.com|xoxy.net|yep.it|yogamaven.com|yopmail.com|yopmail.fr|yopmail.net|yourdomain.com|yuurok.com|z1p.biz|za.com|zehnminuten.de|zehnminutenmail.de|zippymail.info|zoemail.net|zomg.info).)*$')) ~> ValidEmailDomainProfileCa",
                "removeCaColumns sink(allowSchemaDrift: true,",
                "     validateSchema: false,",
                "     deletable:false,",
                "     insertable:true,",
                "     updateable:false,",
                "     upsertable:false,",
                "     recreate:true,",
                "     format: 'document',",
                "     batchSize: 25000,",
                "     partitionKey: ['/email'],",
                "     throughput: 50000,",
                "     skipDuplicateMapInputs: true,",
                "     skipDuplicateMapOutputs: true) ~> SinkGlobalProfile",
                "ValidEmailDomainProfileCa sink(allowSchemaDrift: true,",
                "     validateSchema: false,",
                "     deletable:false,",
                "     insertable:true,",
                "     updateable:false,",
                "     upsertable:false,",
                "     recreate:true,",
                "     format: 'document',",
                "     batchSize: 25000,",
                "     partitionKey: ['/email'],",
                "     throughput: 50000,",
                "     skipDuplicateMapInputs: true,",
                "     skipDuplicateMapOutputs: true) ~> SinkCaProfileRetained",
                "ValidEmailDomainProfileNa sink(allowSchemaDrift: true,",
                "     validateSchema: false,",
                "     deletable:false,",
                "     insertable:true,",
                "     updateable:false,",
                "     upsertable:false,",
                "     recreate:true,",
                "     format: 'document',",
                "     batchSize: 25000,",
                "     partitionKey: ['/email'],",
                "     throughput: 50000,",
                "     skipDuplicateMapInputs: true,",
                "     skipDuplicateMapOutputs: true) ~> SinkNaProfileRetained"
            ]
        }
    }
}